AUTHORS.txt
CHANGES.txt
LICENSE.txt
MANIFEST.in
README.rst
requirements.txt
setup.py
varnishsentry/__init__.py
varnishsentry/api.py
varnishsentry/consumer.py
varnishsentry/worker.py
varnishsentry.egg-info/PKG-INFO
varnishsentry.egg-info/SOURCES.txt
varnishsentry.egg-info/dependency_links.txt
varnishsentry.egg-info/entry_points.txt
varnishsentry.egg-info/requires.txt
varnishsentry.egg-info/top_level.txt
varnishsentry/conf/__init__.py
varnishsentry/conf/default.py
varnishsentry/helpers/__init__.py
varnishsentry/helpers/log.py
varnishsentry/runner/__init__.py
varnishsentry/runner/daemon.py