Metadata-Version: 1.1
Name: varnishsentry
Version: 0.3
Summary: Varnishsentry allows selective submission of grouped varnishd shared memory log entries to Sentry DSNs.
Home-page: https://github.com/carlosabalde/varnishsentry
Author: Carlos Abalde
Author-email: carlos.abalde@gmail.com
License: GPL
Platform: UNKNOWN
Classifier: Intended Audience :: System Administrators
Classifier: Operating System :: OS Independent
